setup.py
noaaport/__init__.py
noaaport/emwin.py
noaaport/log.py
noaaport/nbs.py
noaaport/pipe.py
noaaport/stream.py
noaaport/zis.py
noaaport.egg-info/PKG-INFO
noaaport.egg-info/SOURCES.txt
noaaport.egg-info/dependency_links.txt
noaaport.egg-info/entry_points.txt
noaaport.egg-info/top_level.txt