Metadata-Version: 1.0
Name: noaaport
Version: 1.2.0
Summary: NOAAPORT and EMWIN weather data feed library
Home-page: https://github.com/JeremyGrosser/noaaport
Author: Jeremy Grosser
Author-email: jeremy@synack.me
License: BSD-2-Clause
Platform: UNKNOWN
